asyncio_glib/__init__.py
asyncio_glib/glib_events.py
asyncio_glib/glib_selector.py
asyncio_glib-0.1.dist-info/COPYING.LGPL
asyncio_glib-0.1.dist-info/METADATA
asyncio_glib-0.1.dist-info/WHEEL
asyncio_glib-0.1.dist-info/top_level.txt
asyncio_glib-0.1.dist-info/RECORD
