Metadata-Version: 2.1
Name: asyncio-glib
Version: 0.1
Summary: GLib event loop integration for asyncio
Home-page: https://github.com/jhenstridge/asyncio-glib
Author: James Henstridge
Author-email: james@jamesh.id.au
License: LGPL-2.1+
Platform: UNKNOWN
Classifier: Programming Language :: Python :: 3
Classifier: License :: OSI Approved :: GNU Lesser General Public License v2 or later (LGPLv2+)
Classifier: Operating System :: POSIX
